tabnet_keras/__init__.py
tabnet_keras/attentive_transformer.py
tabnet_keras/decoder.py
tabnet_keras/encoder.py
tabnet_keras/feature_transformer.py
tabnet_keras/gbn.py
tabnet_keras/glu.py
tabnet_keras/models.py
tabnet_keras/split.py
tabnet_keras/utils.py
tabnet_keras/activations/sparsemax.py
tabnet_keras-1.2.0.dist-info/LICENSE
tabnet_keras-1.2.0.dist-info/METADATA
tabnet_keras-1.2.0.dist-info/WHEEL
tabnet_keras-1.2.0.dist-info/top_level.txt
tabnet_keras-1.2.0.dist-info/RECORD
