Metadata-Version: 2.1
Name: tabnet-keras
Version: 1.2.0
Summary: A tf2 keras implementation of tabnet
Author-email: Oleg K <lookout_errands0z@icloud.com>
License: MIT License        
Project-URL: Homepage, https://github.com/OKUA1/tabnet-keras
Project-URL: Bug Tracker, https://github.com/OKUA1/tabnet-keras/issues
Classifier: Programming Language :: Python :: 3
Classifier: License :: OSI Approved :: MIT License
Classifier: Operating System :: OS Independent
Requires-Python: >=3.7
License-File: LICENSE
Requires-Dist: tensorflow (>=2.4.0)
